flask_tinymce/__init__.py
flask_tinymce/static/jquery.tinymce.min.js
flask_tinymce/static/license.txt
flask_tinymce/static/tinymce.d.ts
flask_tinymce/static/tinymce.min.js
flask_tinymce/static/icons/default/icons.min.js
flask_tinymce/static/langs/README.md
flask_tinymce/static/langs/zh_CN.js
flask_tinymce/static/plugins/advlist/plugin.min.js
flask_tinymce/static/plugins/anchor/plugin.min.js
flask_tinymce/static/plugins/autolink/plugin.min.js
flask_tinymce/static/plugins/autoresize/plugin.min.js
flask_tinymce/static/plugins/autosave/plugin.min.js
flask_tinymce/static/plugins/bbcode/plugin.min.js
flask_tinymce/static/plugins/charmap/plugin.min.js
flask_tinymce/static/plugins/code/plugin.min.js
flask_tinymce/static/plugins/codesample/plugin.min.js
flask_tinymce/static/plugins/colorpicker/plugin.min.js
flask_tinymce/static/plugins/contextmenu/plugin.min.js
flask_tinymce/static/plugins/directionality/plugin.min.js
flask_tinymce/static/plugins/emoticons/plugin.min.js
flask_tinymce/static/plugins/emoticons/js/emojiimages.js
flask_tinymce/static/plugins/emoticons/js/emojiimages.min.js
flask_tinymce/static/plugins/emoticons/js/emojis.js
flask_tinymce/static/plugins/emoticons/js/emojis.min.js
flask_tinymce/static/plugins/fullpage/plugin.min.js
flask_tinymce/static/plugins/fullscreen/plugin.min.js
flask_tinymce/static/plugins/help/plugin.min.js
flask_tinymce/static/plugins/hr/plugin.min.js
flask_tinymce/static/plugins/image/plugin.min.js
flask_tinymce/static/plugins/imagetools/plugin.min.js
flask_tinymce/static/plugins/importcss/plugin.min.js
flask_tinymce/static/plugins/insertdatetime/plugin.min.js
flask_tinymce/static/plugins/legacyoutput/plugin.min.js
flask_tinymce/static/plugins/link/plugin.min.js
flask_tinymce/static/plugins/lists/plugin.min.js
flask_tinymce/static/plugins/media/plugin.min.js
flask_tinymce/static/plugins/nonbreaking/plugin.min.js
flask_tinymce/static/plugins/noneditable/plugin.min.js
flask_tinymce/static/plugins/pagebreak/plugin.min.js
Flask_TinyMCE-1.0.0.dist-info/LICENSE
Flask_TinyMCE-1.0.0.dist-info/METADATA
Flask_TinyMCE-1.0.0.dist-info/WHEEL
Flask_TinyMCE-1.0.0.dist-info/top_level.txt
Flask_TinyMCE-1.0.0.dist-info/RECORD
