Metadata-Version: 1.1
Name: Flask-TinyMCE
Version: 1.0.0
Summary: Flask-TinyMCE
Home-page: https://github.com/kanhebei/flask-tinymce
Author: wumao
Author-email: kanhebei@dingtalk.com
License: MIT
Platform: any
Classifier: Environment :: Web Environment
Classifier: Intended Audience :: Developers
Classifier: License :: OSI Approved :: BSD License
Classifier: Operating System :: OS Independent
Classifier: Programming Language :: Python
Classifier: Topic :: Internet :: WWW/HTTP :: Dynamic Content
Classifier: Topic :: Software Development :: Libraries :: Python Modules
